core.py
rcgram-0.3.1.dist-info/METADATA
rcgram-0.3.1.dist-info/WHEEL
rcgram-0.3.1.dist-info/top_level.txt
rcgram-0.3.1.dist-info/RECORD
