Metadata-Version: 2.4
Name: rcgram
Version: 0.3.1
Summary: Async Telegram library with direct access.
Requires-Python: >=3.8
Requires-Dist: httpx
